crate/__init__.py
crate/peewee/__init__.py
crate_peewee-0.1.0.dist-info/DESCRIPTION.rst
crate_peewee-0.1.0.dist-info/METADATA
crate_peewee-0.1.0.dist-info/RECORD
crate_peewee-0.1.0.dist-info/WHEEL
crate_peewee-0.1.0.dist-info/metadata.json
crate_peewee-0.1.0.dist-info/top_level.txt
