Metadata-Version: 2.0
Name: crate-peewee
Version: 0.1.0
Summary: Crate driver for peewee
Home-page: https://github.com/mfussenegger/crate-peewee
Author: Mathias Fußenegger
Author-email: pip@zignar.net
License: UNKNOWN
Platform: any
Classifier: Development Status :: 3 - Alpha
Classifier: Programming Language :: Python :: 3
Classifier: Programming Language :: Python :: 3.5
Requires-Dist: crate
Requires-Dist: peewee
